RDStation/CRM.py
RDStation/Erros.py
RDStation/__init__.py
api_rd_station-0.1.0.dist-info/LICENSE
api_rd_station-0.1.0.dist-info/METADATA
api_rd_station-0.1.0.dist-info/WHEEL
api_rd_station-0.1.0.dist-info/top_level.txt
api_rd_station-0.1.0.dist-info/RECORD
