Metadata-Version: 2.2
Name: api-rd-station
Version: 0.1.0
Summary: Biblioteca para facilitar a integração com a API do RD Station CRM
Home-page: https://github.com/murilochaves/api-rd-station
Author: Murilo Chaves Jayme
Author-email: 
Classifier: Programming Language :: Python :: 3
Classifier: License :: OSI Approved :: MIT License
Classifier: Operating System :: OS Independent
Requires-Python: >=3.6
License-File: LICENSE
Requires-Dist: requests
Requires-Dist: pandas
Dynamic: author
Dynamic: classifier
Dynamic: description
Dynamic: description-content-type
Dynamic: home-page
Dynamic: requires-dist
Dynamic: requires-python
Dynamic: summary
